pyprisma/__init__.py
pyprisma/chat.py
pyprisma-0.0.1.dist-info/LICENSE
pyprisma-0.0.1.dist-info/METADATA
pyprisma-0.0.1.dist-info/WHEEL
pyprisma-0.0.1.dist-info/RECORD
