Metadata-Version: 2.1
Name: pyprisma
Version: 0.0.1
Summary: 🚀PyPrisma: Prisma client for Python
Home-page: https://github.com/Undertone0809/pyprisma
License: MIT
Keywords: PyPrisma,Prisma,Python
Author: Zeeland
Author-email: zeeland4work@gmail.com
Requires-Python: >=3.8.0,<4.0
Classifier: License :: OSI Approved :: MIT License
Classifier: Programming Language :: Python :: 3
Classifier: Programming Language :: Python :: 3.8
Classifier: Programming Language :: Python :: 3.9
Classifier: Programming Language :: Python :: 3.10
Classifier: Programming Language :: Python :: 3.11
Classifier: Programming Language :: Python :: 3.12
Requires-Dist: pne (>=1.1.1,<2.0.0)
Project-URL: Repository, https://github.com/Undertone0809/pyprisma
